IpLocate/__init__.py
IpLocate/iplocate.py
IpLocate/run.py
iplocate-2.3.0.dist-info/LICENSE
iplocate-2.3.0.dist-info/METADATA
iplocate-2.3.0.dist-info/WHEEL
iplocate-2.3.0.dist-info/entry_points.txt
iplocate-2.3.0.dist-info/top_level.txt
iplocate-2.3.0.dist-info/RECORD
