Metadata-Version: 2.1
Name: iplocate
Version: 2.3.0
Summary: 在终端获取本机或者指定ip地址
Home-page: https://github.com/hellflame/iplocate
Author: hellflame
Author-email: hellflamedly@gmail.com
License: MIT
Keywords: ip,ipv4,ipv6,location,ip2location,ip to location
Platform: any
Classifier: Development Status :: 4 - Beta
Classifier: Intended Audience :: Developers
Classifier: License :: OSI Approved :: MIT License
Classifier: Environment :: Console
Classifier: Operating System :: MacOS
Classifier: Operating System :: MacOS :: MacOS X
Classifier: Operating System :: POSIX :: Linux
Classifier: Programming Language :: Python
Classifier: Programming Language :: Python :: 2.7
Classifier: Programming Language :: Python :: 3.4
